ReactEnlightenment/README.md
ReactEnlightenment/__init__.py
ReactEnlightenment/__main__.py
ReactEnlightenment/file.epub
ReactEnlightenment/index.html
ReactEnlightenment/css/__init__.py
ReactEnlightenment/css/annotations.css
ReactEnlightenment/css/main.css
ReactEnlightenment/css/normalize.css
ReactEnlightenment/css/popup.css
ReactEnlightenment/font/__init__.py
ReactEnlightenment/font/fontello.eot
ReactEnlightenment/font/fontello.svg
ReactEnlightenment/font/fontello.ttf
ReactEnlightenment/font/fontello.woff
ReactEnlightenment/img/__init__.py
ReactEnlightenment/img/annotator-glyph-sprite.png
ReactEnlightenment/img/annotator-icon-sprite.png
ReactEnlightenment/img/apple-touch-icon.png
ReactEnlightenment/img/cancelfullscreen.png
ReactEnlightenment/img/close.png
ReactEnlightenment/img/fullscreen.png
ReactEnlightenment/img/loader.gif
ReactEnlightenment/img/menu-icon.png
ReactEnlightenment/img/save.png
ReactEnlightenment/img/saved.png
ReactEnlightenment/img/settings-s.png
ReactEnlightenment/img/settings.png
ReactEnlightenment/img/star.png
ReactEnlightenment/js/__init__.py
ReactEnlightenment/js/epub.js
ReactEnlightenment/js/epub.min.js
ReactEnlightenment/js/epub.min.map
ReactEnlightenment/js/hooks.min.js
ReactEnlightenment/js/hooks.min.map
ReactEnlightenment/js/reader.js
ReactEnlightenment/js/reader.js.map
ReactEnlightenment/js/reader.min.js
ReactEnlightenment/js/reader.min.map
ReactEnlightenment/js/hooks/__init__.py
ReactEnlightenment/js/hooks/extensions/__init__.py
ReactEnlightenment/js/hooks/extensions/highlight.js
ReactEnlightenment/js/libs/__init__.py
ReactEnlightenment/js/libs/jquery.min.js
ReactEnlightenment/js/libs/localforage.min.js
ReactEnlightenment/js/libs/screenfull.js
ReactEnlightenment/js/libs/screenfull.min.js
ReactEnlightenment/js/libs/zip.min.js
ReactEnlightenment/js/plugins/__init__.py
ReactEnlightenment/js/plugins/hypothesis.js
ReactEnlightenment/js/plugins/search.js
react_enlightenment-2024.3.2.0.dist-info/METADATA
react_enlightenment-2024.3.2.0.dist-info/WHEEL
react_enlightenment-2024.3.2.0.dist-info/entry_points.txt
react_enlightenment-2024.3.2.0.dist-info/top_level.txt
react_enlightenment-2024.3.2.0.dist-info/RECORD
